pyembedc/__init__.py
pyembedc-1.26.dist-info/METADATA
pyembedc-1.26.dist-info/RECORD
pyembedc-1.26.dist-info/WHEEL
pyembedc-1.26.dist-info/top_level.txt
