Metadata-Version: 2.1
Name: pyembedc
Version: 1.26
Summary: Embedded C/C++ in Python Source
Home-page: http://github.com/ftrias/pyembedc
Author: Fernando Trias
Author-email: sub@trias.org
License: UNKNOWN
Platform: UNKNOWN
Classifier: License :: OSI Approved :: MIT License
Classifier: Operating System :: OS Independent
